{
  "session_id": "ANL-2026-04-25-l2规则使命宣言业务伤疤融入评判",
  "topic": "评判 L2 规则 [MISSION_STATEMENT] 与 [BUSINESS_LOGIC_CHUNKS] 应如何融入 Fabric-v2",
  "completed": "2026-04-25T23:40:00+08:00",
  "total_rounds": 1,
  "summary": "MISSION_STATEMENT should be added as a first-class L2 Markdown section fetched through the existing L2 required path-triggered rule flow. BUSINESS_LOGIC_CHUNKS should also be a structured L2 section, but requires a separate anchor governance loop: parse @fabric-anchor comments, validate chunk-anchor resolution, warn during pre-commit when anchors disappear, and surface stale/archive diagnostics through doctor. Both blocks should stay out of RuleDescription so plan_context remains a neutral lightweight index.",
  "key_conclusions": [
    {
      "point": "MISSION_STATEMENT fits the existing L2 path-required mechanism.",
      "evidence": "packages/server/src/services/plan-context.ts:37, packages/server/src/services/plan-context.ts:193",
      "confidence": "high"
    },
    {
      "point": "The rule section protocol must be expanded beyond MANDATORY_INJECTION and CONTEXT_INFO.",
      "evidence": "packages/server/src/services/rule-sections.ts:11",
      "confidence": "high"
    },
    {
      "point": "BUSINESS_LOGIC_CHUNKS needs anchor lifecycle governance, not just Markdown injection.",
      "evidence": "packages/cli/src/commands/pre-commit.ts:98",
      "confidence": "high"
    },
    {
      "point": "Dynamic pruning should initially mean stale diagnostics and auditable archival, not silent removal.",
      "evidence": "docs/tooling-manifest.md:13",
      "confidence": "high"
    }
  ],
  "recommendations": [
    {
      "action": "Extend structured rule sections with MISSION_STATEMENT and BUSINESS_LOGIC_CHUNKS",
      "rationale": "The current section fetch API is the right delivery point, but the whitelist currently excludes the proposed blocks.",
      "priority": "high",
      "evidence_refs": [
        "packages/server/src/services/rule-sections.ts:11",
        "packages/server/src/services/rule-sections.test.ts"
      ],
      "steps": [
        {
          "description": "Add the two names to RULE_SECTION_NAMES and update RuleSectionName consumers.",
          "target": "packages/server/src/services/rule-sections.ts",
          "verification": "Parser/service tests can request and receive both sections."
        },
        {
          "description": "Update MCP tool schema section enums.",
          "target": "packages/server/src/tools/rule-sections.ts",
          "verification": "Tool registration tests expose the new enum values."
        },
        {
          "description": "Document section ordering and missing-section diagnostics.",
          "target": "docs/getting-started.md",
          "verification": "Docs describe the recommended fetch order and no-full-content fallback behavior."
        }
      ],
      "review_status": "pending"
    },
    {
      "action": "Define the L2 Markdown contract for mission statements and business chunks",
      "rationale": "The value of both sections depends on predictable structure that agents can parse and humans can review.",
      "priority": "high",
      "evidence_refs": [
        "packages/shared/src/schemas/agents-meta.ts:23",
        "docs/tooling-manifest.md:5"
      ],
      "steps": [
        {
          "description": "Add documentation/template examples for MISSION_STATEMENT fields.",
          "target": "docs/initialization.md",
          "verification": "Docs list Sovereignty, Physical Boundary, Long-term Contract, and Engineering Value."
        },
        {
          "description": "Add documentation/template examples for BUSINESS_LOGIC_CHUNKS fields.",
          "target": "docs/initialization.md",
          "verification": "Docs list ID, Anchor, Intent, Scars, and Constraint."
        },
        {
          "description": "Add test fixtures for non-trivial business chunk parsing.",
          "target": "packages/server/src/services/rule-sections.test.ts",
          "verification": "Fixtures preserve structured chunk text without losing repeated sections."
        }
      ],
      "review_status": "pending"
    },
    {
      "action": "Add @fabric-anchor governance for business chunks",
      "rationale": "The business memory requirement explicitly depends on comments remaining in code even when code moves.",
      "priority": "high",
      "evidence_refs": [
        "packages/cli/src/commands/pre-commit.ts:98",
        "packages/server/src/services/doctor.ts"
      ],
      "steps": [
        {
          "description": "Implement a scanner for @fabric-anchor IDs in source files.",
          "target": "packages/shared or packages/server/src/services",
          "verification": "Tests resolve anchor ID to file and line."
        },
        {
          "description": "Validate BUSINESS_LOGIC_CHUNKS anchors against matched L2 scope files.",
          "target": "packages/server/src/services",
          "verification": "Diagnostics report missing, duplicated, and stale anchors."
        },
        {
          "description": "Wire anchor warnings into pre-commit and detailed reporting into doctor.",
          "target": "packages/cli/src/commands/pre-commit.ts",
          "verification": "Pre-commit test warns when a staged file removes a referenced anchor."
        }
      ],
      "review_status": "pending"
    },
    {
      "action": "Implement conservative chunk merge and pruning semantics",
      "rationale": "Business scars are safety data; automatic deletion should be auditable and reversible.",
      "priority": "medium",
      "evidence_refs": [
        "docs/tooling-manifest.md:13",
        "packages/server/src/services/doctor.ts"
      ],
      "steps": [
        {
          "description": "Treat same chunk ID as replace/upsert.",
          "target": "rule chunk parser or future registry update helper",
          "verification": "Duplicate ID fixtures produce deterministic latest-chunk behavior or diagnostics."
        },
        {
          "description": "Mark missing-anchor chunks as stale.",
          "target": "packages/server/src/services/doctor.ts",
          "verification": "Doctor reports stale business chunks without modifying source."
        },
        {
          "description": "Add explicit archival path for stale chunks.",
          "target": ".fabric/archive/business-logic-chunks.jsonl docs and doctor --fix design",
          "verification": "Archive operation is explicit and ledger/audit visible."
        }
      ],
      "review_status": "pending"
    }
  ],
  "open_questions": [
    "Should missing @fabric-anchor be a warning by default and error under strict config?",
    "Should anchor comments support block comments and language-specific forms beyond //?",
    "Should archived stale chunks live under .fabric/archive/business-logic-chunks.jsonl or in an audit event stream?"
  ],
  "intent_coverage": [
    {
      "intent": "L2 MISSION_STATEMENT first-layer identity confirmation",
      "status": "addressed",
      "where_addressed": "Recommendation 1 and 2",
      "notes": "Use L2 required selection plus first section ordering."
    },
    {
      "intent": "Physical boundary and long-term contract",
      "status": "addressed",
      "where_addressed": "Recommendation 2",
      "notes": "Defined as Markdown contract fields."
    },
    {
      "intent": "BUSINESS_LOGIC_CHUNKS as business intuition patch",
      "status": "addressed",
      "where_addressed": "Recommendation 2 and 3",
      "notes": "Section carries memory, anchor governance carries lifecycle."
    },
    {
      "intent": "Semantic merge and dynamic pruning",
      "status": "transformed",
      "where_addressed": "Recommendation 4",
      "notes": "Initial implementation should use deterministic upsert and auditable stale archive."
    },
    {
      "intent": "@fabric-anchor binding and commit warning",
      "status": "addressed",
      "where_addressed": "Recommendation 3",
      "notes": "Requires new pre-commit/doctor diagnostics."
    }
  ],
  "findings_coverage": [
    {
      "finding": "L2 required path trigger already exists",
      "round": 1,
      "disposition": "recommendation",
      "target": "Rec #1",
      "reason": "MISSION_STATEMENT can reuse this trigger."
    },
    {
      "finding": "Section whitelist lacks the new names",
      "round": 1,
      "disposition": "recommendation",
      "target": "Rec #1",
      "reason": "Service/tool schema must be expanded."
    },
    {
      "finding": "Business chunks require anchor lifecycle checks",
      "round": 1,
      "disposition": "recommendation",
      "target": "Rec #3",
      "reason": "Commit warning cannot be achieved by section injection alone."
    },
    {
      "finding": "Dynamic pruning should not silently delete scars",
      "round": 1,
      "disposition": "recommendation",
      "target": "Rec #4",
      "reason": "Historical business memory must remain auditable."
    },
    {
      "finding": "Tooling manifest is precedent but not target registry",
      "round": 1,
      "disposition": "informational",
      "target": "Design reference only",
      "reason": "It confirms script-boundary knowledge is useful, but intentionally separate from agents.meta."
    }
  ],
  "decision_trail": [
    {
      "round": 1,
      "decision": "Use section protocol for both proposed L2 blocks.",
      "context": "Existing rule section API already serves structured Markdown sections after path context is known.",
      "options_considered": [
        "RuleDescription fields",
        "AgentsMetaNode metadata",
        "Markdown sections"
      ],
      "chosen": "Markdown sections returned by fab_get_rule_sections",
      "rejected_reasons": "RuleDescription should remain lightweight and neutral; agents.meta should not store business正文.",
      "reason": "Lowest-friction integration with existing L2 required selection.",
      "impact": "Implementation scope starts in rule-sections service/tool/tests."
    },
    {
      "round": 1,
      "decision": "Add separate anchor governance for BUSINESS_LOGIC_CHUNKS.",
      "context": "User requires deletion of @fabric-anchor comments to trigger commit warning.",
      "options_considered": [
        "Prompt-only preservation instruction",
        "Pre-commit warning",
        "Doctor-only report"
      ],
      "chosen": "Pre-commit warning plus doctor diagnostics",
      "rejected_reasons": "Prompt-only behavior is not enforceable; doctor-only feedback is too late for commit-time warning.",
      "reason": "Matches existing Fabric governance pattern around human-lint and doctor.",
      "impact": "Requires new anchor parser and diagnostics."
    }
  ]
}
